audioopy/__init__.py
audioopy/audio.py
audioopy/audioconvert.py
audioopy/audioframes.py
audioopy/audioopyexc.py
audioopy/audioutils.py
audioopy/audiovolume.py
audioopy/basevolume.py
audioopy/channel.py
audioopy/channelformatter.py
audioopy/channelframes.py
audioopy/channelsmixer.py
audioopy/channelvolume.py
audioopy/po.py
audioopy/aio/__init__.py
audioopy/aio/audiofactory.py
audioopy/aio/waveio.py
audioopy/ipus/__init__.py
audioopy/ipus/channelsilences.py
audioopy/ipus/searchfor.py
audioopy/po/en/LC_MESSAGES/audioopy.mo
audioopy/po/fr/LC_MESSAGES/audioopy.mo
audioopy/scripts/__init__.py
audioopy/scripts/audioextract.py
audioopy/scripts/audioformat.py
audioopy/scripts/audiofragment.py
audioopy/scripts/audioinfo.py
audioopy/scripts/audioipus.py
audioopy/scripts/audiomixer.py
audioopy/scripts/audioresample.py
audioopy-0.6.dist-info/licenses/AUTHORS.md
audioopy-0.6.dist-info/licenses/LICENSE.md
audioopy-0.6.dist-info/METADATA
audioopy-0.6.dist-info/WHEEL
audioopy-0.6.dist-info/entry_points.txt
audioopy-0.6.dist-info/top_level.txt
audioopy-0.6.dist-info/RECORD
