Metadata-Version: 2.4
Name: AudiooPy
Version: 0.6
Summary: Audio manager in Python Object-Oriented Programming
Author-email: Brigitte Bigi <contact@sppas.org>
Project-URL: Homepage, https://audioopy.sourceforge.io/
Project-URL: Repository, https://sourceforge.net/projects/audioopy/
Keywords: python,class,module,audio,mixer,wav,channel,frames,extract,ipus
Classifier: Programming Language :: Python :: 3
Classifier: License :: OSI Approved :: GNU General Public License v3 or later (GPLv3+)
Classifier: Operating System :: OS Independent
Classifier: Topic :: Documentation
Classifier: Topic :: Software Development :: Documentation
Classifier: Intended Audience :: Developers
Classifier: Development Status :: 5 - Production/Stable
Requires-Python: >=2.7
License-File: LICENSE.md
License-File: AUTHORS.md
Provides-Extra: docs
Requires-Dist: pygments; extra == "docs"
Requires-Dist: markdown2; extra == "docs"
Requires-Dist: Clamming==2.0; extra == "docs"
Provides-Extra: tests
Requires-Dist: coverage~=7.3.0; extra == "tests"
Requires-Dist: python-dotenv~=1.0.0; extra == "tests"
Dynamic: license-file
